Metadata-Version: 2.1
Name: chatmysql
Version: 0.1.18
Summary: A simple chat cli based on mysql cli.
Home-page: https://github.com/DataMini/cmysql
Author: lele
Requires-Dist: langchain (==0.0.340)
Requires-Dist: prettytable (~=3.7.0)
Requires-Dist: pydantic (~=1.10.9)
Requires-Dist: neo4j (~=5.12.0)
Requires-Dist: qdrant-client (~=1.6.4)
Requires-Dist: SQLAlchemy (~=2.0.22)
Requires-Dist: httpx (~=0.23.3)
Requires-Dist: Jinja2 (~=3.1.2)
Requires-Dist: openai (~=1.2.2)
Requires-Dist: setuptools (~=65.7.0)
Requires-Dist: pymysql
